dpdata_qdpi/__init__.py
dpdata_qdpi/dftb3.py
dpdata_qdpi/dftbpapi.py
dpdata_qdpi/qdpi.py
dpdata_qdpi-0.0.2.dist-info/LICENSE
dpdata_qdpi-0.0.2.dist-info/METADATA
dpdata_qdpi-0.0.2.dist-info/WHEEL
dpdata_qdpi-0.0.2.dist-info/entry_points.txt
dpdata_qdpi-0.0.2.dist-info/top_level.txt
dpdata_qdpi-0.0.2.dist-info/RECORD
