Metadata-Version: 2.1
Name: dpdata_qdpi
Version: 0.0.2
Summary: The dpdata plugin for QDPi.
License: GNU LESSER GENERAL PUBLIC LICENSE
Project-URL: Homepage, https://github.com/njzjz/dpdata_qdpi
Classifier: Programming Language :: Python
Classifier: Programming Language :: Python :: 3
Requires-Python: >=3.7
License-File: LICENSE
Requires-Dist: dpdata >=0.2.7
Requires-Dist: ase >=3.23.0
Requires-Dist: deepmd-kit
Provides-Extra: cpu
Requires-Dist: deepmd-kit[cpu] >=2.2.0b0 ; extra == 'cpu'
Provides-Extra: gpu
Requires-Dist: deepmd-kit[gpu] >=2.2.0b0 ; extra == 'gpu'
Provides-Extra: test
Requires-Dist: pytest ; extra == 'test'
Requires-Dist: pytest-cov ; extra == 'test'
